llm_api_access-0.1.23.dist-info/METADATA
llm_api_access-0.1.23.dist-info/WHEEL
llm_api_access/__init__.py
llm_api_access/llm_api_access.cpython-38-x86_64-linux-gnu.so
llm_api_access-0.1.23.dist-info/RECORD
