Metadata-Version: 2.4
Name: llm_api_access
Version: 0.1.23
Summary: A package to query popular LLMs
License: MIT OR Apache-2.0
Project-URL: Source Code, https://github.com/scionsamurai/llm_api_crate
